hw2/generator_la/generator_latex/__init__.py
hw2/generator_la/generator_latex/gen_latext.py
latex_generator_ts-0.4.0.dist-info/METADATA
latex_generator_ts-0.4.0.dist-info/WHEEL
latex_generator_ts-0.4.0.dist-info/top_level.txt
latex_generator_ts-0.4.0.dist-info/RECORD
