Metadata-Version: 2.1
Name: latex-generator-ts
Version: 0.4.0
Summary: A library for generating LaTeX tables and images.
Home-page: UNKNOWN
Author: Katya Ts
Author-email: ekaterinatsr@gmail.com
License: UNKNOWN
Platform: UNKNOWN
Classifier: Programming Language :: Python :: 3
Classifier: License :: OSI Approved :: MIT License
Classifier: Operating System :: OS Independent
Requires-Python: >=3.9
